llama_index/readers/slack/__init__.py
llama_index/readers/slack/base.py
flying_delta_readers_slack-0.1.0.dist-info/METADATA
flying_delta_readers_slack-0.1.0.dist-info/WHEEL
flying_delta_readers_slack-0.1.0.dist-info/RECORD
